{
    "@id": "dtmi:com:ngsi-ld:EVChargingStation;0",
    "@type": "Interface",
    "@context": "dtmi:dtdl:context;2",
    "comment": "Smart Data Models - Transportation / EV Charging Station adapted to DTDL from smartdatamodels.org. Source: https://raw.githubusercontent.com/smart-data-models/dataModel.Transportation/master/EVChargingStation/schema.json",
    "description": "EV Charging Station",
    "displayName": "EVChargingStation",
    "contents": [
        {
            "name": "alternateName",
            "writable": true,
            "displayName": "alternateName",
            "@type": "Property",
            "schema": "string",
            "comment": "An alternative name for this item"
        },
        {
            "name": "amountCollected",
            "writable": true,
            "displayName": "amountCollected",
            "@type": "Property",
            "schema": "long",
            "comment": "Amount collected towards the service corresponding to this observation."
        },
        {
            "name": "amperage",
            "writable": true,
            "displayName": "amperage",
            "@type": "Property",
            "schema": "long",
            "comment": "The total amperage offered by the charging station."
        },
        {
            "name": "areaServed",
            "writable": true,
            "displayName": "areaServed",
            "@type": "Property",
            "schema": "string",
            "comment": "The geographic area where a service or offered item is provided"
        },
        {
            "name": "availableCapacity",
            "writable": true,
            "displayName": "availableCapacity",
            "@type": "Property",
            "schema": "integer",
            "comment": "The number of vehicles which currently can be charged. It must lower or equal than `capacity`."
        },
        {
            "name": "capacity",
            "writable": true,
            "displayName": "capacity",
            "@type": "Property",
            "schema": "integer",
            "comment": "The total number of vehicles which can be charged at the same time. The total number of sockets can be higher. "
        },
        {
            "name": "chargingUnitId",
            "writable": true,
            "displayName": "chargingUnitId",
            "@type": "Property",
            "schema": "string",
            "comment": "The Id of the charging point in the EV charging station corresponding to this observation."
        },
        {
            "name": "dataDescriptor",
            "writable": true,
            "displayName": "dataDescriptor",
            "@type": "Relationship",
            "comment": "URI pointing to the data-descriptor entity"
        },
        {
            "name": "dataProvider",
            "writable": true,
            "displayName": "dataProvider",
            "@type": "Property",
            "schema": "string",
            "comment": "A sequence of characters identifying the provider of the harmonised data entity."
        },
        {
            "name": "dateCreated",
            "writable": true,
            "displayName": "dateCreated",
            "@type": "Property",
            "schema": "dateTime",
            "comment": "Entity creation timestamp. This will usually be allocated by the storage platform."
        },
        {
            "name": "dateModified",
            "writable": true,
            "displayName": "dateModified",
            "@type": "Property",
            "schema": "dateTime",
            "comment": "Timestamp of the last modification of the entity. This will usually be allocated by the storage platform."
        },
        {
            "name": "description",
            "writable": true,
            "displayName": "description",
            "@type": "Property",
            "schema": "string",
            "comment": "A description of this item"
        },
        {
            "name": "endDateTime",
            "writable": true,
            "displayName": "endDateTime",
            "@type": "Property",
            "schema": "dateTime",
            "comment": "Reported end time corresponding to this observation."
        },
        {
            "name": "name",
            "writable": true,
            "displayName": "name",
            "@type": "Property",
            "schema": "string",
            "comment": "The name of this item."
        },
        {
            "name": "network",
            "writable": true,
            "displayName": "network",
            "@type": "Property",
            "schema": "string",
            "comment": "The name of the Network, with that the operator cooperates. "
        },
        {
            "name": "observationDateTime",
            "writable": true,
            "displayName": "observationDateTime",
            "@type": "Property",
            "schema": "dateTime",
            "comment": "Last reported time of observation."
        },
        {
            "name": "openingHours",
            "writable": true,
            "displayName": "openingHours",
            "@type": "Property",
            "schema": "string",
            "comment": "Opening hours of the charging station. "
        },
        {
            "name": "operator",
            "writable": true,
            "displayName": "operator",
            "@type": "Property",
            "schema": "string",
            "comment": "Charging station's operator. "
        },
        {
            "name": "powerConsumption",
            "writable": true,
            "displayName": "powerConsumption",
            "@type": "Property",
            "schema": "long",
            "comment": "Power consumed by the entity corresponding to this observation."
        },
        {
            "name": "seeAlso",
            "writable": true,
            "displayName": "seeAlso"
        },
        {
            "name": "socketNumber",
            "writable": true,
            "displayName": "socketNumber",
            "@type": "Property",
            "schema": "integer",
            "comment": "The total number of sockets offered by this charging station"
        },
        {
            "name": "source",
            "writable": true,
            "displayName": "source",
            "@type": "Property",
            "schema": "string",
            "comment": "A sequence of characters giving the original source of the entity data as a URL. Recommended to be the fully qualified domain name of the source provider, or the URL to the source object."
        },
        {
            "name": "startDateTime",
            "writable": true,
            "displayName": "startDateTime",
            "@type": "Property",
            "schema": "dateTime",
            "comment": "Reported start time corresponding to this observation."
        },
        {
            "name": "stationName",
            "writable": true,
            "displayName": "stationName",
            "@type": "Property",
            "schema": "string",
            "comment": "The name station corresponding to this observation. It can be the name of bike docking station, charging station, etc."
        },
        {
            "name": "taxAmountCollected",
            "writable": true,
            "displayName": "taxAmountCollected",
            "@type": "Property",
            "schema": "long",
            "comment": "The amount of tax levied on the products, things and services which includes sales tax, value-added tax, service tax, Good and Service tax, customs duty, etc."
        },
        {
            "name": "transactionId",
            "writable": true,
            "displayName": "transactionId",
            "@type": "Property",
            "schema": "string",
            "comment": "Unique transaction Id of the entity corresponding to this observation."
        },
        {
            "name": "transactionType",
            "writable": true,
            "displayName": "transactionType",
            "@type": "Property",
            "schema": "string",
            "comment": "Type of the transaction based on the mode of payment (For eg. mobile/UPI, card, etc) or mode of service (For eg. Issue, ReIssue, Entry, Exit etc.) corresponding to this observation."
        },
        {
            "name": "voltage",
            "writable": true,
            "displayName": "voltage",
            "@type": "Property",
            "schema": "long",
            "comment": "The total voltage offered by the charging station"
        },
        {
            "@type": "Telemetry",
            "name": "acceptedPaymentMethod",
            "schema": {
                "@type": "Array",
                "elementSchema": "string"
            },
            "comment": "Type(s) of charge when using this station. Enum:'ByBankTransferInAdvance, ByInvoice, Cash, CheckInAdvance, COD, DirectDebit, GoogleCheckout, PayPal, PaySwarm'",
            "displayName": "acceptedPaymentMethod"
        },
        {
            "@type": "Telemetry",
            "name": "allowedVehicleType",
            "schema": {
                "@type": "Array",
                "elementSchema": "string"
            },
            "comment": "Vehicle type(s) which can be charged. Enum:'bicycle, bus, car, caravan, motorcycle, motorscooter, truck' ",
            "displayName": "allowedVehicleType"
        },
        {
            "@type": "Telemetry",
            "name": "chargeType",
            "schema": {
                "@type": "Array",
                "elementSchema": "string"
            },
            "comment": "Type(s) of charge when using this station. Enum:'annualPayment, flat, free, monthlyPayment, other'",
            "displayName": "chargeType"
        },
        {
            "@type": "Telemetry",
            "name": "owner",
            "schema": {
                "@type": "Array",
                "elementSchema": "string"
            },
            "comment": "A List containing a JSON encoded sequence of characters referencing the unique Ids of the owner(s)",
            "displayName": "owner"
        },
        {
            "@type": "Telemetry",
            "name": "socketType",
            "schema": {
                "@type": "Array",
                "elementSchema": "string"
            },
            "comment": "The type of sockets offered by this station. Enum:'Caravan_Mains_Socket, CHAdeMO, CCS/SAE, Dual_CHAdeMO, Dual_J-1772, Dual_Mennekes, J-1772, Mennekes, Other, Tesla, Type2, Type3, Wall_Euro'",
            "displayName": "socketType"
        },
        {
            "@type": "object",
            "name": "address",
            "comment": "The mailing address",
            "displayName": "address",
            "fields": [
                {
                    "name": "addressCountry",
                    "schema": "string"
                },
                {
                    "name": "addressLocality",
                    "schema": "string"
                },
                {
                    "name": "addressRegion",
                    "schema": "string"
                },
                {
                    "name": "postOfficeBoxNumber",
                    "schema": "string"
                },
                {
                    "name": "postalCode",
                    "schema": "string"
                },
                {
                    "name": "streetAddress",
                    "schema": "string"
                }
            ]
        },
        {
            "@type": "object",
            "name": "contactPoint",
            "comment": "The details to contact with the item.",
            "displayName": "contactPoint",
            "fields": [
                {
                    "name": "areaServed",
                    "schema": "string"
                },
                {
                    "name": "availabilityRestriction",
                    "schema": "array"
                },
                {
                    "name": "availableLanguage",
                    "schema": "string"
                },
                {
                    "name": "contactOption",
                    "schema": "string"
                },
                {
                    "name": "contactType",
                    "schema": "string"
                },
                {
                    "name": "email",
                    "schema": "string"
                },
                {
                    "name": "faxNumber",
                    "schema": "string"
                },
                {
                    "name": "name",
                    "schema": "string"
                },
                {
                    "name": "productSupported",
                    "schema": "string"
                },
                {
                    "name": "telephone",
                    "schema": "string"
                },
                {
                    "name": "url",
                    "schema": "string"
                }
            ]
        },
        {
            "@type": "Telemetry",
            "name": "location_Point",
            "schema": "point"
        },
        {
            "@type": "Telemetry",
            "name": "location_LineString",
            "schema": "lineString"
        },
        {
            "@type": "Telemetry",
            "name": "location_Polygon",
            "schema": "polygon"
        },
        {
            "@type": "Telemetry",
            "name": "location_MultiPoint",
            "schema": "multiPoint"
        },
        {
            "@type": "Telemetry",
            "name": "location_MultiLineString",
            "schema": "multiLineString"
        },
        {
            "@type": "Telemetry",
            "name": "location_MultiPolygon",
            "schema": "multiPolygon"
        },
        {
            "@type": "Telemetry",
            "name": "status",
            "schema": {
                "@type": "Enum",
                "valueSchema": "string",
                "enumValues": [
                    {
                        "name": "almostEmpty",
                        "displayName": "almostEmpty",
                        "enumValue": 1
                    },
                    {
                        "name": "almostFull",
                        "displayName": "almostFull",
                        "enumValue": 2
                    },
                    {
                        "name": "empty",
                        "displayName": "empty",
                        "enumValue": 3
                    },
                    {
                        "name": "full",
                        "displayName": "full",
                        "enumValue": 4
                    },
                    {
                        "name": "outOfService",
                        "displayName": "outOfService",
                        "enumValue": 5
                    },
                    {
                        "name": "withIncidence",
                        "displayName": "withIncidence",
                        "enumValue": 6
                    },
                    {
                        "name": "working",
                        "displayName": "working",
                        "enumValue": 7
                    }
                ]
            }
        },
        {
            "@type": "Telemetry",
            "name": "vehicleType",
            "schema": {
                "@type": "Enum",
                "valueSchema": "string",
                "enumValues": [
                    {
                        "name": "agriculturalVehicle",
                        "displayName": "agriculturalVehicle",
                        "enumValue": 1
                    },
                    {
                        "name": "ambulance",
                        "displayName": "ambulance",
                        "enumValue": 2
                    },
                    {
                        "name": "articulatedVehicle",
                        "displayName": "articulatedVehicle",
                        "enumValue": 3
                    },
                    {
                        "name": "autorickshaw",
                        "displayName": "autorickshaw",
                        "enumValue": 4
                    },
                    {
                        "name": "bicycle",
                        "displayName": "bicycle",
                        "enumValue": 5
                    },
                    {
                        "name": "binTrolley",
                        "displayName": "binTrolley",
                        "enumValue": 6
                    },
                    {
                        "name": "BRT bus",
                        "displayName": "BRT bus",
                        "enumValue": 7
                    },
                    {
                        "name": "BRT minibus",
                        "displayName": "BRT minibus",
                        "enumValue": 8
                    },
                    {
                        "name": "bus",
                        "displayName": "bus",
                        "enumValue": 9
                    },
                    {
                        "name": "car",
                        "displayName": "car",
                        "enumValue": 10
                    },
                    {
                        "name": "caravan",
                        "displayName": "caravan",
                        "enumValue": 11
                    },
                    {
                        "name": "carOrLightVehicle",
                        "displayName": "carOrLightVehicle",
                        "enumValue": 12
                    },
                    {
                        "name": "carWithCaravan",
                        "displayName": "carWithCaravan",
                        "enumValue": 13
                    },
                    {
                        "name": "carWithTrailer",
                        "displayName": "carWithTrailer",
                        "enumValue": 14
                    },
                    {
                        "name": "cleaningTrolley",
                        "displayName": "cleaningTrolley",
                        "enumValue": 15
                    },
                    {
                        "name": "compactor",
                        "displayName": "compactor",
                        "enumValue": 16
                    },
                    {
                        "name": "constructionOrMaintenanceVehicle",
                        "displayName": "constructionOrMaintenanceVehicle",
                        "enumValue": 17
                    },
                    {
                        "name": "dumper",
                        "displayName": "dumper",
                        "enumValue": 18
                    },
                    {
                        "name": "e-moped",
                        "displayName": "e-moped",
                        "enumValue": 19
                    },
                    {
                        "name": "e-scooter",
                        "displayName": "e-scooter",
                        "enumValue": 20
                    },
                    {
                        "name": "e-motorcycle",
                        "displayName": "e-motorcycle",
                        "enumValue": 21
                    },
                    {
                        "name": "fire tender",
                        "displayName": "fire tender",
                        "enumValue": 22
                    },
                    {
                        "name": "fourWheelDrive",
                        "displayName": "fourWheelDrive",
                        "enumValue": 23
                    },
                    {
                        "name": "highSidedVehicle",
                        "displayName": "highSidedVehicle",
                        "enumValue": 24
                    },
                    {
                        "name": "hopper",
                        "displayName": "hopper",
                        "enumValue": 25
                    },
                    {
                        "name": "lorry",
                        "displayName": "lorry",
                        "enumValue": 26
                    },
                    {
                        "name": "minibus",
                        "displayName": "minibus",
                        "enumValue": 27
                    },
                    {
                        "name": "moped",
                        "displayName": "moped",
                        "enumValue": 28
                    },
                    {
                        "name": "motorcycle",
                        "displayName": "motorcycle",
                        "enumValue": 29
                    },
                    {
                        "name": "motorcycleWithSideCar",
                        "displayName": "motorcycleWithSideCar",
                        "enumValue": 30
                    },
                    {
                        "name": "motorscooter",
                        "displayName": "motorscooter",
                        "enumValue": 31
                    },
                    {
                        "name": "police van",
                        "displayName": "police van",
                        "enumValue": 32
                    },
                    {
                        "name": "sweepingMachine",
                        "displayName": "sweepingMachine",
                        "enumValue": 33
                    },
                    {
                        "name": "tanker",
                        "displayName": "tanker",
                        "enumValue": 34
                    },
                    {
                        "name": "tempo",
                        "displayName": "tempo",
                        "enumValue": 35
                    },
                    {
                        "name": "threeWheeledVehicle",
                        "displayName": "threeWheeledVehicle",
                        "enumValue": 36
                    },
                    {
                        "name": "tipper",
                        "displayName": "tipper",
                        "enumValue": 37
                    },
                    {
                        "name": "trailer",
                        "displayName": "trailer",
                        "enumValue": 38
                    },
                    {
                        "name": "tram",
                        "displayName": "tram",
                        "enumValue": 39
                    },
                    {
                        "name": "twoWheeledVehicle",
                        "displayName": "twoWheeledVehicle",
                        "enumValue": 40
                    },
                    {
                        "name": "trolley",
                        "displayName": "trolley",
                        "enumValue": 41
                    },
                    {
                        "name": "van",
                        "displayName": "van",
                        "enumValue": 42
                    }
                ]
            }
        }
    ]
}